basicpy/__init__.py
basicpy/__main__.py
basicpy/_jax_routines.py
basicpy/basicpy.py
basicpy/datasets.py
basicpy/metrics.py
basicpy/types.py
basicpy/tools/__init__.py
basicpy/tools/_jax_idct.py
basicpy/tools/dct_tools.py
BaSiCPy-1.2.0.dist-info/LICENSE
BaSiCPy-1.2.0.dist-info/METADATA
BaSiCPy-1.2.0.dist-info/WHEEL
BaSiCPy-1.2.0.dist-info/entry_points.txt
BaSiCPy-1.2.0.dist-info/top_level.txt
BaSiCPy-1.2.0.dist-info/RECORD
