Metadata-Version: 2.1
Name: BaSiCPy
Version: 1.2.0
Summary: A python package for background and shading correction of optical microscopy images
Home-page: https://github.com/peng-lab/BaSiCPy
Author: Nicholas Schaub, Tim Morello, Tingying Peng, Yohsuke T. Fukai
Author-email: nick.schaub@nih.gov, timothy.morello@downstate.edu, tingying.peng@helmholtz-muenchen.de, ysk@yfukai.net
License: MIT
Project-URL: Bug Tracker, https://github.com/peng-lab/BaSiCPy/issues
Keywords: background shading flatfield darkfield biology optical microscopy image illumination
Classifier: Development Status :: 4 - Beta
Classifier: License :: OSI Approved :: MIT License
Classifier: Operating System :: OS Independent
Classifier: Programming Language :: Python :: 3
Classifier: Programming Language :: Python :: 3 :: Only
Requires-Python: >=3.8
License-File: LICENSE
Requires-Dist: hyperactive >=4.4.0
Requires-Dist: jax <=0.4.23,>=0.3.10
Requires-Dist: jaxlib <=0.4.23,>=0.3.10
Requires-Dist: numpy
Requires-Dist: pooch
Requires-Dist: pydantic <3.0.0,>=2.7.0
Requires-Dist: scikit-image
Requires-Dist: scipy <1.13
Provides-Extra: dask
Requires-Dist: dask ; extra == 'dask'
Provides-Extra: dev
Requires-Dist: black ; extra == 'dev'
Requires-Dist: bump2version ; extra == 'dev'
Requires-Dist: darglint ; extra == 'dev'
Requires-Dist: dask ; extra == 'dev'
Requires-Dist: flake8 ; extra == 'dev'
Requires-Dist: flake8-alphabetize ; extra == 'dev'
Requires-Dist: flake8-black ; extra == 'dev'
Requires-Dist: flake8-docstrings ; extra == 'dev'
Requires-Dist: flake8-isort ; extra == 'dev'
Requires-Dist: flake8-markdown ; extra == 'dev'
Requires-Dist: flake8-pytest ; extra == 'dev'
Requires-Dist: isort ; extra == 'dev'
Requires-Dist: mypy ; extra == 'dev'
Requires-Dist: nox ; extra == 'dev'
Requires-Dist: pre-commit ; extra == 'dev'
Requires-Dist: pytest ; extra == 'dev'
Requires-Dist: pytest-benchmark ; extra == 'dev'
Requires-Dist: pytest-cov ; extra == 'dev'
Requires-Dist: pytest-datadir ; extra == 'dev'
Requires-Dist: xdoctest ; extra == 'dev'
